__init__.py
apps.py
channels.py
consumers.py
decorators.py
exceptions.py
mongo.py
redis.py
related_properties.py
signal_handler.py
state_loader.py
state_model.py
transaction.py
websocket_router.py
management/__init__.py
management/commands/__init__.py
management/commands/makefrontend.py
ts/__init__.py
ts/channels.py
ts/interfaces.py
rxdjango-0.0.7.dist-info/LICENSE.md
rxdjango-0.0.7.dist-info/METADATA
rxdjango-0.0.7.dist-info/WHEEL
rxdjango-0.0.7.dist-info/top_level.txt
rxdjango-0.0.7.dist-info/RECORD
