Metadata-Version: 2.1
Name: rxdjango
Version: 0.0.7
Summary: A Django layer to synchronize models between back and frontend
Author-email: Luis Fagundes <lhfagundes@gmail.com>
Project-URL: Homepage, https://github.com/CDIGlobalTrack/rxdjango
Project-URL: Bug Tracker, https://github.com/CDIGlobalTrack/rxdjango/issues
Classifier: Programming Language :: Python :: 3
Classifier: License :: OSI Approved :: MIT License
Classifier: Operating System :: OS Independent
Requires-Python: >=3.10
License-File: LICENSE.md
